umb/__about__.py
umb/__init__.py
umb/api.py
umb/config.py
umb/exceptions.py
umb/http_client.py
umb/utils.py
umb-1.0.1.dist-info/DESCRIPTION.rst
umb-1.0.1.dist-info/METADATA
umb-1.0.1.dist-info/RECORD
umb-1.0.1.dist-info/WHEEL
umb-1.0.1.dist-info/metadata.json
umb-1.0.1.dist-info/top_level.txt
